BaomuJiShenduXuexiCongRumenDaoFangqi/README.md
BaomuJiShenduXuexiCongRumenDaoFangqi/__init__.py
BaomuJiShenduXuexiCongRumenDaoFangqi/__main__.py
BaomuJiShenduXuexiCongRumenDaoFangqi/file.epub
BaomuJiShenduXuexiCongRumenDaoFangqi/index.html
BaomuJiShenduXuexiCongRumenDaoFangqi/css/__init__.py
BaomuJiShenduXuexiCongRumenDaoFangqi/css/annotations.css
BaomuJiShenduXuexiCongRumenDaoFangqi/css/main.css
BaomuJiShenduXuexiCongRumenDaoFangqi/css/normalize.css
BaomuJiShenduXuexiCongRumenDaoFangqi/css/popup.css
BaomuJiShenduXuexiCongRumenDaoFangqi/font/__init__.py
BaomuJiShenduXuexiCongRumenDaoFangqi/font/fontello.eot
BaomuJiShenduXuexiCongRumenDaoFangqi/font/fontello.svg
BaomuJiShenduXuexiCongRumenDaoFangqi/font/fontello.ttf
BaomuJiShenduXuexiCongRumenDaoFangqi/font/fontello.woff
BaomuJiShenduXuexiCongRumenDaoFangqi/img/__init__.py
BaomuJiShenduXuexiCongRumenDaoFangqi/img/annotator-glyph-sprite.png
BaomuJiShenduXuexiCongRumenDaoFangqi/img/annotator-icon-sprite.png
BaomuJiShenduXuexiCongRumenDaoFangqi/img/apple-touch-icon.png
BaomuJiShenduXuexiCongRumenDaoFangqi/img/cancelfullscreen.png
BaomuJiShenduXuexiCongRumenDaoFangqi/img/close.png
BaomuJiShenduXuexiCongRumenDaoFangqi/img/fullscreen.png
BaomuJiShenduXuexiCongRumenDaoFangqi/img/loader.gif
BaomuJiShenduXuexiCongRumenDaoFangqi/img/menu-icon.png
BaomuJiShenduXuexiCongRumenDaoFangqi/img/save.png
BaomuJiShenduXuexiCongRumenDaoFangqi/img/saved.png
BaomuJiShenduXuexiCongRumenDaoFangqi/img/settings-s.png
BaomuJiShenduXuexiCongRumenDaoFangqi/img/settings.png
BaomuJiShenduXuexiCongRumenDaoFangqi/img/star.png
BaomuJiShenduXuexiCongRumenDaoFangqi/js/__init__.py
BaomuJiShenduXuexiCongRumenDaoFangqi/js/epub.js
BaomuJiShenduXuexiCongRumenDaoFangqi/js/epub.min.js
BaomuJiShenduXuexiCongRumenDaoFangqi/js/epub.min.map
BaomuJiShenduXuexiCongRumenDaoFangqi/js/hooks.min.js
BaomuJiShenduXuexiCongRumenDaoFangqi/js/hooks.min.map
BaomuJiShenduXuexiCongRumenDaoFangqi/js/reader.js
BaomuJiShenduXuexiCongRumenDaoFangqi/js/reader.js.map
baomu_ji_shendu_xuexi_cong_rumen_dao_fangqi-2024.3.5.0.dist-info/METADATA
baomu_ji_shendu_xuexi_cong_rumen_dao_fangqi-2024.3.5.0.dist-info/WHEEL
baomu_ji_shendu_xuexi_cong_rumen_dao_fangqi-2024.3.5.0.dist-info/entry_points.txt
baomu_ji_shendu_xuexi_cong_rumen_dao_fangqi-2024.3.5.0.dist-info/top_level.txt
baomu_ji_shendu_xuexi_cong_rumen_dao_fangqi-2024.3.5.0.dist-info/RECORD
